ws/mastodump/__init__.py
ws/mastodump/backup.py
ws/mastodump/connection.py
ws_mastodump-1.0.1.dist-info/METADATA
ws_mastodump-1.0.1.dist-info/WHEEL
ws_mastodump-1.0.1.dist-info/entry_points.txt
ws_mastodump-1.0.1.dist-info/licenses/LICENSE
ws_mastodump-1.0.1.dist-info/RECORD
