Metadata-Version: 2.1
Name: ws.mastodump
Version: 1.0.1
Summary: Incremental export of mastodon posts and boosts to plain text
Project-URL: repository, https://github.com/wosc/mastodump
Author-email: Wolfgang Schnerring <wosc@wosc.de>
License:  GPL-3.0-or-later
License-File: LICENSE
Requires-Dist: mastodon-py
